LICENSE
README.md
pyproject.toml
setup.cfg
src/remote_etc_hosts/__init__.py
src/remote_etc_hosts/api.py
src/remote_etc_hosts/cli.py
src/remote_etc_hosts/exceptions.py
src/remote_etc_hosts/utils.py
src/remote_etc_hosts.egg-info/PKG-INFO
src/remote_etc_hosts.egg-info/SOURCES.txt
src/remote_etc_hosts.egg-info/dependency_links.txt
src/remote_etc_hosts.egg-info/entry_points.txt
src/remote_etc_hosts.egg-info/requires.txt
src/remote_etc_hosts.egg-info/top_level.txt